setup.py
chompy/__init__.py
chompy.egg-info/PKG-INFO
chompy.egg-info/SOURCES.txt
chompy.egg-info/dependency_links.txt
chompy.egg-info/top_level.txt