Metadata-Version: 1.0
Name: chompy
Version: 1.0.0
Summary: A chomp function for Python
Home-page: UNKNOWN
Author: Brian Lauber
Author-email: constructible.truth@gmail.com
License: UNKNOWN
Platform: UNKNOWN
